mixentropy/np/__init__.py
mixentropy/np/elk_estimator.py
mixentropy/np/kde_estimator.py
mixentropy/np/logdet_estimator.py
mixentropy/np/monte_carlo_estimator.py
mixentropy/np/pairwise_dist_estimator.py
mixentropy/pth/__init__.py
mixentropy/pth/elk_estimator.py
mixentropy/pth/kde_estimator.py
mixentropy/pth/logdet_estimator.py
mixentropy/pth/monte_carlo_estimator.py
mixentropy/pth/pairwise_dist_estimator.py
mixentropy-0.0.1.dist-info/LICENSE
mixentropy-0.0.1.dist-info/METADATA
mixentropy-0.0.1.dist-info/WHEEL
mixentropy-0.0.1.dist-info/top_level.txt
mixentropy-0.0.1.dist-info/RECORD
