Metadata-Version: 2.1
Name: mixentropy
Version: 0.0.1
Summary: Tools for estimating entropy of mixture distribution and more.
Author-email: Grizxly <grizxlyzx@gamil.com>
Maintainer-email: Grizxly <grizxlyzx@gamil.com>
License: MIT License
Project-URL: Repository, https://github.com/grizxlyzx/MixEntroPY
Keywords: machine learning,deep learning,entropy
Classifier: Programming Language :: Python :: 3
Requires-Python: >=3.8
License-File: LICENSE
Requires-Dist: numpy >=1.20.0
Provides-Extra: pth
Requires-Dist: torch >=2.0.0 ; extra == 'pth'
